niche_cv/__init__.py
niche_cv/detr.py
niche_cv/device.py
niche_cv/show.py
niche_cv/detection/__init__.py
niche_cv/detection/data/__init__.py
niche_cv/detection/data/shuffle_balloon.py
niche_cv/detection/data/balloon/__init__.py
niche_cv/detection/data/splitter/__init__.py
niche_cv/detection/data/splitter/coco.py
niche_cv/detection/data/splitter/splitter.py
niche_cv/detection/data/splitter/yolo.py
niche_cv/detection/models/__init__.py
niche_cv/detection/models/detr.py
niche_cv/detection/models/mrcnn.py
niche_cv/detection/models/yolo.py
niche_cv-0.0.11.dist-info/LICENSE
niche_cv-0.0.11.dist-info/METADATA
niche_cv-0.0.11.dist-info/WHEEL
niche_cv-0.0.11.dist-info/entry_points.txt
niche_cv-0.0.11.dist-info/top_level.txt
niche_cv-0.0.11.dist-info/RECORD
