Metadata-Version: 2.1
Name: niche_cv
Version: 0.0.11
Summary: The Computer Vision Library for Niche Squad
Home-page: https://github.com/Niche-Squad/niche_cv
Author: James Chen
Author-email: niche@vt.edu
License-File: LICENSE
